qingcloud_sdk-1.2.16-py2.7-nspkg.pth
qingcloud/app/__init__.py
qingcloud/app/connection.py
qingcloud/app/constants.py
qingcloud/conn/__init__.py
qingcloud/conn/auth.py
qingcloud/conn/connection.py
qingcloud/iaas/__init__.py
qingcloud/iaas/connection.py
qingcloud/iaas/consolidator.py
qingcloud/iaas/constants.py
qingcloud/iaas/errors.py
qingcloud/iaas/lb_backend.py
qingcloud/iaas/lb_listener.py
qingcloud/iaas/monitor.py
qingcloud/iaas/router_static.py
qingcloud/iaas/sg_rule.py
qingcloud/iaas/actions/__init__.py
qingcloud/iaas/actions/alarm_policy.py
qingcloud/iaas/actions/cluster.py
qingcloud/iaas/actions/eip.py
qingcloud/iaas/actions/image.py
qingcloud/iaas/actions/instance.py
qingcloud/iaas/actions/instance_groups.py
qingcloud/iaas/actions/keypair.py
qingcloud/iaas/actions/loadbalancer.py
qingcloud/iaas/actions/migrate.py
qingcloud/iaas/actions/nic.py
qingcloud/iaas/actions/router.py
qingcloud/iaas/actions/s2.py
qingcloud/iaas/actions/sdwan.py
qingcloud/iaas/actions/security_group.py
qingcloud/iaas/actions/snapshot.py
qingcloud/iaas/actions/tag.py
qingcloud/iaas/actions/volume.py
qingcloud/iaas/actions/vpc_border.py
qingcloud/iaas/actions/vxnet.py
qingcloud/misc/__init__.py
qingcloud/misc/json_tool.py
qingcloud/misc/utils.py
qingcloud/qai/__init__.py
qingcloud/qai/connection.py
qingcloud/qai/constants.py
qingcloud/qingstor/__init__.py
qingcloud/qingstor/acl.py
qingcloud/qingstor/bucket.py
qingcloud/qingstor/connection.py
qingcloud/qingstor/exception.py
qingcloud/qingstor/key.py
qingcloud/qingstor/multipart.py
qingcloud/qingstor/util.py
qingcloud_sdk-1.2.16.dist-info/LICENSE
qingcloud_sdk-1.2.16.dist-info/METADATA
qingcloud_sdk-1.2.16.dist-info/NOTICE
qingcloud_sdk-1.2.16.dist-info/WHEEL
qingcloud_sdk-1.2.16.dist-info/namespace_packages.txt
qingcloud_sdk-1.2.16.dist-info/top_level.txt
qingcloud_sdk-1.2.16.dist-info/RECORD
