Metadata-Version: 2.1
Name: qingcloud-sdk
Version: 1.2.16
Summary: Software Development Kit for QingCloud.
Home-page: https://docs.qingcloud.com/sdk/
Author: Yunify Team
Author-email: simon@yunify.com
License: UNKNOWN
Keywords: qingcloud iaas qingstor sdk
Platform: UNKNOWN
Requires-Dist: future
Requires-Dist: requests
